{"AQI":{"天津":"182","石家庄":"152","唐山":"157","秦皇岛":"105","邯郸":"90","保定":"149","张家口":"89","承德":"113","廊坊":"169","沧州":"161","衡水":"121","邢台":"131","太原":"84","呼和浩特":"74","沈阳":"93","大连":"54","长春":"55","哈尔滨":"37","上海":"43","南京":"66","苏州":"51","南通":"48","连云港":"98","徐州":"100","扬州":"70","无锡":"44","常州":"51","镇江":"72","泰州":"74","淮安":"91","盐城":"105","宿迁":"93","杭州":"41","宁波":"45","温州":"58","绍兴":"47","湖州":"49","嘉兴":"44","台州":"54","舟山":"41","金华":"46.0","衢州":"31","丽水":"31.0","合肥":"53","福州":"37","厦门":"46","南昌":"31","济南":"93","青岛":"81","郑州":"82","武汉":"62","长沙":"72","广州":"50","深圳":"46","珠海":"17","佛山":"66","中山":"36.0","江门":"53","东莞":"47","惠州":"36","肇庆":"77","南宁":"53","海口":"21","重庆":"57","成都":"95","贵阳":"39","昆明":"52","拉萨":"174","西安":"51","兰州":"58","西宁":"77","银川":"58","乌鲁木齐":"26","北京":"111.0","湘潭":"103","株洲":"113","河源":"30","清远":"22.0","营口":"71","丹东":"73","盘锦":"132","玉溪":"46","包头":"102","鄂尔多斯":"87","葫芦岛":"145","泉州":"25","莱芜":"116","德州":"134","聊城":"112.0","滨州":"144.0","临沂":"140","枣庄":"96","烟台":"129","淄博":"115","潍坊":"116","济宁":"140","威海":"110","东营":"205","汕头":"28","泰安":"103","日照":"66","大同":"106","阳泉":"111","临汾":"134","柳州":"69","长治":"65","咸阳":"44","铜川":"59","北海":"45","渭南":"57","延安":"162","宝鸡":"105","韶关":"34","菏泽":"94","湛江":"35","茂名":"27","梅州":"29","汕尾":"46","阳江":"22","潮州":"30","揭阳":"36","云浮":"42","宜昌":"78","荆州":"143","赤峰":"89","克拉玛依":"44","库尔勒":"60","齐齐哈尔":"41","牡丹江":"41","曲靖":"43","九江":"19","金昌":"57","嘉峪关":"60.0","洛阳":"106","安阳":"90","开封":"94","焦作":"102","平顶山":"78","三门峡":"94","遵义":"33","吴江":"35","昆山":"37","常熟":"38","张家港":"56","太仓":"41","句容":"63","江阴":"56.0","宜兴":"30","金坛":"55","溧阳":"53","海门":"46","岳阳":"96","常德":"110","张家界":"83","绵阳":"91","宜宾":"110","攀枝花":"58","泸州":"148","自贡":"155","德阳":"66","南充":"103","三亚":"28","吉林":"49","石嘴山":"92","临安":"50","富阳":"30","义乌":"42","诸暨":"43","鞍山":"95","抚顺":"79","本溪":"87","锦州":"194","瓦房店":"67.0","桂林":"56","芜湖":"57","胶州":"105","章丘":"93","即墨":"68","平度":"444","胶南":"","莱西":"185","莱州":"88","蓬莱":"102","招远":"141","寿光":"94","文登":"176","荣成":"152","乳山":"103.0","马鞍山":"63","大庆":"44"},"PM2.5":{"天津":"137","石家庄":"116","唐山":"119","秦皇岛":"73","邯郸":"56","保定":"114","张家口":"25","承德":"85","廊坊":"128","沧州":"122","衡水":"57","邢台":"97","太原":"55","呼和浩特":"41","沈阳":"69","大连":"24","长春":"26","哈尔滨":"17","上海":"30","南京":"42","苏州":"28","南通":"32","连云港":"73","徐州":"41","扬州":"50","无锡":"24","常州":"29","镇江":"32","泰州":"54","淮安":"42","盐城":"78","宿迁":"69","杭州":"21","宁波":"19","温州":"11","绍兴":"16","湖州":"31","嘉兴":"27","台州":"22","舟山":"18","金华":"32.0","衢州":"17","丽水":"22.0","合肥":"37","福州":"15","厦门":"32","南昌":"14","济南":"53","青岛":"54","郑州":"60","武汉":"44","长沙":"47","广州":"29","深圳":"21","珠海":"8","佛山":"47","中山":"20.0","江门":"34","东莞":"33","惠州":"17","肇庆":"56","南宁":"23","海口":"12","重庆":"31","成都":"71","贵阳":"22","昆明":"27","拉萨":"74","西安":"24","兰州":"41","西宁":"56","银川":"36","乌鲁木齐":"17","北京":"83.0","湘潭":"77","株洲":"85","河源":"16","清远":"14.0","营口":"42","丹东":"53","盘锦":"100","玉溪":"18","包头":"54","鄂尔多斯":"59","葫芦岛":"111","泉州":"9","莱芜":"87","德州":"102","聊城":"64.0","滨州":"110.0","临沂":"106","枣庄":"71","烟台":"98","淄博":"83","潍坊":"72","济宁":"107","威海":"82","东营":"53","汕头":"11","泰安":"77","日照":"47","大同":"79","阳泉":"72","临汾":"102","柳州":"50","长治":"37","咸阳":"19","铜川":"33","北海":"9","渭南":"24","延安":"123","宝鸡":"78","韶关":"24","菏泽":"64","湛江":"17","茂名":"11","梅州":"15","汕尾":"12","阳江":"11","潮州":"21","揭阳":"25","云浮":"23","宜昌":"57","荆州":"109","赤峰":"45","克拉玛依":"15","库尔勒":"17","齐齐哈尔":"11","牡丹江":"27","曲靖":"19","九江":"12","金昌":"23","嘉峪关":"24.0","洛阳":"51","安阳":"67","开封":"64","焦作":"76","平顶山":"51","三门峡":"70","遵义":"18","吴江":"17","昆山":"19","常熟":"21","张家港":"32","太仓":"17","句容":"45","江阴":"39.0","宜兴":"17","金坛":"27","溧阳":"18","海门":"25","岳阳":"68","常德":"82","张家界":"61","绵阳":"68","宜宾":"82","攀枝花":"41","泸州":"113","自贡":"118","德阳":"47","南充":"77","三亚":"11","吉林":"18","石嘴山":"62","临安":"17","富阳":"21","义乌":"26","诸暨":"19","鞍山":"71","抚顺":"58","本溪":"64","锦州":"146","瓦房店":"48.0","桂林":"39","芜湖":"26","胶州":"78","章丘":"34","即墨":"25","平度":"70","胶南":"","莱西":"139","莱州":"60","蓬莱":"76","招远":"108","寿光":"70","文登":"133","荣成":"116","乳山":"77.0","马鞍山":"33","大庆":"21"},"PM10":{"天津":"177","石家庄":"222","唐山":"178","秦皇岛":"159","邯郸":"129","保定":"209","张家口":"69","承德":"149","廊坊":"226","沧州":"144","衡水":"183","邢台":"211","太原":"117","呼和浩特":"96","沈阳":"124","大连":"56","长春":"58","哈尔滨":"36","上海":"35","南京":"81","苏州":"50","南通":"47","连云港":"125","徐州":"79","扬州":"88","无锡":"43","常州":"50","镇江":"93","泰州":"77","淮安":"84","盐城":"105","宿迁":"123","杭州":"40","宁波":"38","温州":"17","绍兴":"31","湖州":"48","嘉兴":"43","台州":"30","舟山":"34","金华":"35.0","衢州":"27","丽水":"17.0","合肥":"44","福州":"36","厦门":"33","南昌":"19","济南":"134","青岛":"110","郑州":"112","武汉":"68","长沙":"92","广州":"49","深圳":"45","珠海":"17","佛山":"70","中山":"35.0","江门":"55","东莞":"40","惠州":"35","肇庆":"73","南宁":"55","海口":"21","重庆":"62","成都":"113","贵阳":"38","昆明":"53","拉萨":"296","西安":"51","兰州":"48","西宁":"75","银川":"63","乌鲁木齐":"25","北京":"163.0","湘潭":"126","株洲":"112","河源":"19","清远":"20.0","营口":"91","丹东":"90","盘锦":"110","玉溪":"45","包头":"152","鄂尔多斯":"108","葫芦岛":"158","泉州":"23","莱芜":"163","德州":"155","聊城":"173.0","滨州":"179.0","临沂":"228","枣庄":"141","烟台":"137","淄博":"179","潍坊":"180","济宁":"187","威海":"131","东营":"353","汕头":"27","泰安":"107","日照":"69","大同":"120","阳泉":"171","临汾":"154","柳州":"78","长治":"79","咸阳":"43","铜川":"66","北海":"36","渭南":"62","延安":"205","宝鸡":"134","韶关":"28","菏泽":"137","湛江":"34","茂名":"26","梅州":"23","汕尾":"22","阳江":"22","潮州":"29","揭阳":"28","云浮":"41","宜昌":"92","荆州":"197","赤峰":"126","克拉玛依":"22","库尔勒":"68","齐齐哈尔":"37","牡丹江":"40","曲靖":"34","九江":"15","金昌":"62","嘉峪关":"69.0","洛阳":"100","安阳":"109","开封":"136","焦作":"124","平顶山":"79","三门峡":"95","遵义":"32","吴江":"34","昆山":"32","常熟":"33","张家港":"61","太仓":"31","句容":"48","江阴":"51.0","宜兴":"29","金坛":"50","溧阳":"54","海门":"31","岳阳":"140","常德":"105","张家界":"92","绵阳":"75","宜宾":"129","攀枝花":"41","泸州":"135","自贡":"181","德阳":"66","南充":"115","三亚":"20","吉林":"48","石嘴山":"133","临安":"47","富阳":"28","义乌":"41","诸暨":"34","鞍山":"116","抚顺":"102","本溪":"106","锦州":"156","瓦房店":"42.0","桂林":"48","芜湖":"62","胶州":"101","章丘":"61","即墨":"65","平度":"543","胶南":"","莱西":"182","莱州":"115","蓬莱":"126","招远":"162","寿光":"137","文登":"144","荣成":"162","乳山":"89.0","马鞍山":"75","大庆":"32"},"SO2":{"天津":"41","石家庄":"60","唐山":"82","秦皇岛":"29","邯郸":"37","保定":"45","张家口":"229","承德":"15","廊坊":"47","沧州":"51","衡水":"30","邢台":"98","太原":"24","呼和浩特":"43","沈阳":"58","大连":"2","长春":"10","哈尔滨":"16","上海":"9","南京":"28","苏州":"11","南通":"15","连云港":"23","徐州":"30","扬州":"40","无锡":"17","常州":"30","镇江":"30","泰州":"28","淮安":"33","盐城":"20","宿迁":"33","杭州":"27","宁波":"7","温州":"2","绍兴":"12","湖州":"19","嘉兴":"18","台州":"3","舟山":"5","金华":"12.0","衢州":"12","丽水":"5.0","合肥":"18","福州":"5","厦门":"9","南昌":"13","济南":"33","青岛":"15","郑州":"16","武汉":"203","长沙":"11","广州":"16","深圳":"6","珠海":"5","佛山":"22","中山":"8.0","江门":"32","东莞":"13","惠州":"17","肇庆":"40","南宁":"12","海口":"3","重庆":"14","成都":"5","贵阳":"7","昆明":"21","拉萨":"13","西安":"7","兰州":"10","西宁":"27","银川":"21","乌鲁木齐":"3","北京":"17.0","湘潭":"15","株洲":"28","河源":"6","清远":"18.0","营口":"6","丹东":"10","盘锦":"10","玉溪":"16","包头":"42","鄂尔多斯":"21","葫芦岛":"17","泉州":"5","莱芜":"70","德州":"76","聊城":"24.0","滨州":"145.0","临沂":"110","枣庄":"44","烟台":"21","淄博":"169","潍坊":"50","济宁":"200","威海":"26","东营":"85","汕头":"6","泰安":"66","日照":"8","大同":"20","阳泉":"43","临汾":"39","柳州":"59","长治":"13","咸阳":"14","铜川":"8","北海":"13","渭南":"25","延安":"15","宝鸡":"13","韶关":"12","菏泽":"47","湛江":"19","茂名":"4","梅州":"8","汕尾":"6","阳江":"2","潮州":"9","揭阳":"17","云浮":"9","宜昌":"16","荆州":"18","赤峰":"15","克拉玛依":"2","库尔勒":"23","齐齐哈尔":"43","牡丹江":"5","曲靖":"19","九江":"24","金昌":"5","嘉峪关":"15.0","洛阳":"14","安阳":"37","开封":"26","焦作":"61","平顶山":"33","三门峡":"30","遵义":"7","吴江":"11","昆山":"19","常熟":"12","张家港":"16","太仓":"22","句容":"12","江阴":"77.0","宜兴":"24","金坛":"24","溧阳":"25","海门":"9","岳阳":"18","常德":"27","张家界":"10","绵阳":"9","宜宾":"23","攀枝花":"16","泸州":"21","自贡":"14","德阳":"15","南充":"16","三亚":"1","吉林":"5","石嘴山":"29","临安":"5","富阳":"8","义乌":"12","诸暨":"3","鞍山":"14","抚顺":"18","本溪":"13","锦州":"67","瓦房店":"1.0","桂林":"7","芜湖":"31","胶州":"11","章丘":"40","即墨":"73","平度":"19","胶南":"","莱西":"8","莱州":"26","蓬莱":"15","招远":"51","寿光":"26","文登":"16","荣成":"28","乳山":"13.0","马鞍山":"24","大庆":"6"},"NO2":{"天津":"65","石家庄":"58","唐山":"51","秦皇岛":"67","邯郸":"42","保定":"22","张家口":"22","承德":"42","廊坊":"35","沧州":"16","衡水":"39","邢台":"92","太原":"41","呼和浩特":"49","沈阳":"41","大连":"19","长春":"31","哈尔滨":"31","上海":"19","南京":"33","苏州":"25","南通":"34","连云港":"23","徐州":"22","扬州":"39","无锡":"29","常州":"56","镇江":"46","泰州":"35","淮安":"21","盐城":"25","宿迁":"25","杭州":"40","宁波":"14","温州":"11","绍兴":"32","湖州":"45","嘉兴":"29","台州":"9","舟山":"12","金华":"21.0","衢州":"13","丽水":"24.0","合肥":"19","福州":"30","厦门":"19","南昌":"17","济南":"50","青岛":"17","郑州":"43","武汉":"41","长沙":"25","广州":"49","深圳":"32","珠海":"17","佛山":"73","中山":"17.0","江门":"35","东莞":"38","惠州":"26","肇庆":"66","南宁":"30","海口":"8","重庆":"30","成都":"36","贵阳":"19","昆明":"33","拉萨":"5","西安":"18","兰州":"21","西宁":"19","银川":"13","乌鲁木齐":"45","北京":"67.0","湘潭":"39","株洲":"41","河源":"36","清远":"13.0","营口":"14","丹东":"7","盘锦":"22","玉溪":"28","包头":"32","鄂尔多斯":"15","葫芦岛":"29","泉州":"15","莱芜":"78","德州":"35","聊城":"24.0","滨州":"","临沂":"118","枣庄":"31","烟台":"22","淄博":"76","潍坊":"60","济宁":"45","威海":"20","东营":"64","汕头":"22","泰安":"34","日照":"25","大同":"28","阳泉":"29","临汾":"35","柳州":"27","长治":"16","咸阳":"24","铜川":"30","北海":"12","渭南":"32","延安":"71","宝鸡":"30","韶关":"29","菏泽":"24","湛江":"11","茂名":"4","梅州":"16","汕尾":"18","阳江":"2","潮州":"15","揭阳":"27","云浮":"21","宜昌":"33","荆州":"70","赤峰":"9","克拉玛依":"5","库尔勒":"4","齐齐哈尔":"7","牡丹江":"12","曲靖":"13","九江":"14","金昌":"3","嘉峪关":"23.0","洛阳":"38","安阳":"54","开封":"28","焦作":"40","平顶山":"28","三门峡":"6","遵义":"16","吴江":"30","昆山":"28","常熟":"28","张家港":"26","太仓":"8","句容":"18","江阴":"46.0","宜兴":"21","金坛":"34","溧阳":"28","海门":"12","岳阳":"17","常德":"25","张家界":"9","绵阳":"26","宜宾":"30","攀枝花":"11","泸州":"44","自贡":"16","德阳":"16","南充":"26","三亚":"2","吉林":"15","石嘴山":"9","临安":"25","富阳":"18","义乌":"45","诸暨":"15","鞍山":"11","抚顺":"45","本溪":"33","锦州":"36","瓦房店":"7.0","桂林":"13","芜湖":"15","胶州":"35","章丘":"27","即墨":"40","平度":"70","胶南":"","莱西":"50","莱州":"16","蓬莱":"23","招远":"41","寿光":"38","文登":"19","荣成":"23","乳山":"20.0","马鞍山":"23","大庆":"14"}}
