{"AQI":{"北京":"267","天津":"149","石家庄":"287","唐山":"234","秦皇岛":"147","邯郸":"149","保定":"349","张家口":"36","承德":"165","廊坊":"231","沧州":"244","衡水":"350","邢台":"419","太原":"77","呼和浩特":"48","沈阳":"109","大连":"83","长春":"113","哈尔滨":"163","上海":"81","南京":"53","苏州":"75","南通":"94","连云港":"141","徐州":"91","扬州":"70","无锡":"78","常州":"72","镇江":"74","泰州":"89","淮安":"125","盐城":"93","宿迁":"100","杭州":"72","宁波":"61","温州":"52","绍兴":"59","湖州":"78","嘉兴":"78","台州":"76","舟山":"49","金华":"49","衢州":"67","丽水":"40","合肥":"70","福州":"42","厦门":"29","南昌":"50","济南":"124","青岛":"100","郑州":"226","武汉":"119","长沙":"65.0","广州":"35","深圳":"43","珠海":"53.0","佛山":"29","中山":"33","江门":"48.0","东莞":"35","惠州":"35","肇庆":"26","南宁":"33","海口":"27","重庆":"65","成都":"53","贵阳":"88","昆明":"37","拉萨":"66","西安":"113","兰州":"44","西宁":"32","银川":"104","乌鲁木齐":"114","湘潭":"67","株洲":"54","包头":"64","鄂尔多斯":"115","营口":"41","盘锦":"79","泉州":"35.0","莱芜":"172","临沂":"132","德州":"295","聊城":"131","滨州":"222","淄博":"139","枣庄":"89","烟台":"111","潍坊":"139","济宁":"98","泰安":"113","日照":"102","威海":"101","东营":"191","韶关":"31","汕头":"38","湛江":"22","茂名":"27","梅州":"30.0","汕尾":"32","阳江":"33","清远":"39","潮州":"76.0","云浮":"19","玉溪":"35","菏泽":"93","大同":"63","长治":"54","临汾":"101","阳泉":"95","赤峰":"82","鞍山":"72","抚顺":"81","本溪":"61","锦州":"80","吉林":"108","齐齐哈尔":"87","牡丹江":"78","大庆":"53","芜湖":"53","马鞍山":"59","九江":"66","洛阳":"219","安阳":"226","开封":"92","焦作":"252","平顶山":"175","三门峡":"153","宜昌":"131","荆州":"150","岳阳":"81","常德":"97","张家界":"100","桂林":"56","北海":"60","柳州":"117","三亚":"27","绵阳":"43","宜宾":"74","攀枝花":"58","泸州":"86","自贡":"75","德阳":"35","南充":"65","遵义":"67","曲靖":"52","咸阳":"100","铜川":"198","延安":"145","宝鸡":"124","渭南":"86","金昌":"64","嘉峪关":"57","石嘴山":"145","克拉玛依":"66","库尔勒":"500.0","寿光":"150","章丘":"136","即墨":"119","胶南":"98","胶州":"94","莱西":"117","平度":"121","蓬莱":"100","招远":"94","莱州":"150","荣成":"72","文登":"81","乳山":"81","吴江":"77","昆山":"81","常熟":"86","张家港":"104","太仓":"85","句容":"54.0","江阴":"98","宜兴":"59","金坛":"63","溧阳":"72","海门":"97","临安":"71","富阳":"67","义乌":"59","诸暨":"","瓦房店":"63","信阳":"75","周口":"104","漳州":"35.0","晋城":"68","朔州":"92","晋中":"199","运城":"117","忻州":"42","吕梁":"81","乌海":"89","通辽":"46","呼伦贝尔":"70","巴彦淖尔":"57","乌兰察布":"48","兴安盟":"139","锡林郭勒盟":"50","阿拉善盟":"130","阜新":"157","铁岭":"113","四平":"156","辽源":"72","通化":"60","白山":"78","松原":"69","白城":"142.0","延边州":"54.0","鸡西":"66","鹤岗":"178","双鸭山":"108","伊春":"45","佳木斯":"71","七台河":"92.0","黑河":"92","绥化":"52","大兴安岭地区":"66.0","蚌埠":"66","淮南":"69","淮北":"72","铜陵":"58","安庆":"55","黄山":"","滁州":"46","阜阳":"55","宿州":"75","六安":"63","亳州":"104.0","池州":"40","宣城":"65","莆田":"40","三明":"32","南平":"47","龙岩":"27","宁德":"35.0","景德镇":"66","萍乡":"96","新余":"59","鹰潭":"37","赣州":"55","吉安":"55","宜春":"61","抚州":"76","上饶":"42","鹤壁":"135","新乡":"254","濮阳":"127","许昌":"217.0","漯河":"128","南阳":"81","商丘":"81","驻马店":"115","黄石":"83","十堰":"86","鄂州":"108","荆门":"164","孝感":"181","黄冈":"105","咸宁":"115","随州":"136","恩施州":"63","衡阳":"81","邵阳":"67","益阳":"65","郴州":"85","永州":"78","怀化":"55","娄底":"83","湘西州":"74","梧州":"38","防城港":"43","钦州":"30","贵港":"47","玉林":"49.0","百色":"65","贺州":"83","河池":"81","来宾":"103","崇左":"46.0","广元":"18","遂宁":"46","内江":"80","乐山":"53","眉山":"64","广安":"56","达州":"94","雅安":"54","巴中":"48","资阳":"54","阿坝州":"49","甘孜州":"47.0","凉山州":"59","六盘水":"116","安顺":"51","铜仁地区":"57","毕节":"38","黔西南州":"62","黔东南州":"44","黔南州":"33","保山":"82.0","昭通":"79","丽江":"48","临沧":"53.0","楚雄州":"33","红河州":"61","文山州":"63.0","西双版纳州":"77","大理州":"58.0","德宏州":"67","怒江州":"37","迪庆州":"33","昌都地区":"86","山南地区":"42","日喀则地区":"179.0","那曲地区":"38.0","阿里地区":"52","林芝地区":"42.0","汉中":"75","榆林":"464","安康":"50","商洛":"87","白银":"108","天水":"120","武威":"95","张掖":"110","平凉":"85","酒泉":"65","庆阳":"91","定西":"48","陇南":"64","临夏州":"52","甘南州":"105","海东地区":"60","海北州":"105","黄南州":"106","海南州":"70","果洛州":"114","玉树州":"45.0","海西州":"154","吴忠":"161","中卫":"132","固原":"93","吐鲁番地区":"118","哈密地区":"81.0","昌吉州":"46","博州":"74","阿克苏地区":"132.0","喀什地区":"197","和田地区":"196","伊犁哈萨克州":"72","塔城地区":"47.0","阿勒泰地区":"58.0","石河子":"179.0","五家渠":"40","克州":"173","普洱":"56","襄阳":"196","葫芦岛":"109","河源":"28","揭阳":"36","辽阳":"62","朝阳":"","丹东":"135"},"PM2.5":{"北京":"216","天津":"114","石家庄":"236","唐山":"183","秦皇岛":"112","邯郸":"114","保定":"263","张家口":"12","承德":"125","廊坊":"180","沧州":"193","衡水":"243","邢台":"285","太原":"56","呼和浩特":"12","沈阳":"81","大连":"46","长春":"84","哈尔滨":"123","上海":"46","南京":"34","苏州":"54","南通":"64","连云港":"107","徐州":"67","扬州":"50","无锡":"55","常州":"52","镇江":"53","泰州":"66","淮安":"94","盐城":"65","宿迁":"75","杭州":"44","宁波":"30","温州":"29","绍兴":"36","湖州":"45","嘉兴":"47","台州":"52","舟山":"17","金华":"34","衢州":"25","丽水":"28","合肥":"50","福州":"8","厦门":"16","南昌":"35","济南":"93","青岛":"75","郑州":"175","武汉":"89","长沙":"46.0","广州":"24","深圳":"30","珠海":"36.0","佛山":"20","中山":"23","江门":"33.0","东莞":"24","惠州":"20","肇庆":"14","南宁":"23","海口":"14","重庆":"46","成都":"36","贵阳":"65","昆明":"19","拉萨":"47","西安":"74","兰州":"24","西宁":"19","银川":"35","乌鲁木齐":"85","湘潭":"47","株洲":"30","包头":"14","鄂尔多斯":"33","营口":"15","盘锦":"56","泉州":"17.0","莱芜":"130","临沂":"100","德州":"244","聊城":"99","滨州":"171","淄博":"106","枣庄":"66","烟台":"83","潍坊":"106","济宁":"73","泰安":"84","日照":"75","威海":"59","东营":"143","韶关":"21","汕头":"19","湛江":"14","茂名":"18","梅州":"21.0","汕尾":"21","阳江":"17","清远":"27","潮州":"55.0","云浮":"13","玉溪":"16","菏泽":"69","大同":"27","长治":"28","临汾":"64","阳泉":"65","赤峰":"60","鞍山":"47","抚顺":"59","本溪":"34","锦州":"41","吉林":"80","齐齐哈尔":"64","牡丹江":"57","大庆":"36","芜湖":"36","马鞍山":"41","九江":"47","洛阳":"168","安阳":"175","开封":"68","焦作":"201","平顶山":"132","三门峡":"116","宜昌":"99","荆州":"115","岳阳":"43","常德":"72","张家界":"75","桂林":"39","北海":"42","柳州":"88","三亚":"17","绵阳":"30","宜宾":"53","攀枝花":"31","泸州":"63","自贡":"54","德阳":"24","南充":"46","遵义":"48","曲靖":"15","咸阳":"69","铜川":"148","延安":"49","宝鸡":"93","渭南":"60","金昌":"15","嘉峪关":"22","石嘴山":"51","克拉玛依":"18","库尔勒":"111.0","寿光":"115","章丘":"103","即墨":"89","胶南":"73","胶州":"70","莱西":"88","平度":"91","蓬莱":"75","招远":"69","莱州":"115","荣成":"33","文登":"38","乳山":"32","吴江":"47","昆山":"51","常熟":"61","张家港":"77","太仓":"52","句容":"31.0","江阴":"73","宜兴":"35","金坛":"44","溧阳":"44","海门":"62","临安":"47","富阳":"48","义乌":"41","诸暨":"","瓦房店":"40","信阳":"54","周口":"77","漳州":"22.0","晋城":"33","朔州":"68","晋中":"149","运城":"88","忻州":"11","吕梁":"59","乌海":"43","通辽":"31","呼伦贝尔":"50","巴彦淖尔":"30","乌兰察布":"27","兴安盟":"106","锡林郭勒盟":"24","阿拉善盟":"60","阜新":"119","铁岭":"84","四平":"118","辽源":"52","通化":"39","白山":"57","松原":"49","白城":"108.0","延边州":"37.0","鸡西":"28","鹤岗":"134","双鸭山":"80","伊春":"14","佳木斯":"43","七台河":"64.0","黑河":"68","绥化":"34","大兴安岭地区":"47.0","蚌埠":"47","淮南":"49","淮北":"52","铜陵":"40","安庆":"37","黄山":"","滁州":"32","阜阳":"38","宿州":"54","六安":"44","亳州":"77.0","池州":"28","宣城":"46","莆田":"28","三明":"19","南平":"31","龙岩":"17","宁德":"16.0","景德镇":"47","萍乡":"71","新余":"40","鹰潭":"22","赣州":"38","吉安":"38","宜春":"43","抚州":"55","上饶":"29","鹤壁":"102","新乡":"203","濮阳":"96","许昌":"166.0","漯河":"97","南阳":"59","商丘":"59","驻马店":"86","黄石":"61","十堰":"63","鄂州":"80","荆门":"124","孝感":"136","黄冈":"78","咸宁":"86","随州":"103","恩施州":"44","衡阳":"59","邵阳":"48","益阳":"36","郴州":"62","永州":"57","怀化":"35","娄底":"61","湘西州":"53","梧州":"23","防城港":"30","钦州":"20","贵港":"26","玉林":"34.0","百色":"46","贺州":"61","河池":"59","来宾":"76","崇左":"32.0","广元":"8","遂宁":"28","内江":"58","乐山":"36","眉山":"45","广安":"34","达州":"70","雅安":"31","巴中":"28","资阳":"23","阿坝州":"23","甘孜州":"12.0","凉山州":"34","六盘水":"87","安顺":"23","铜仁地区":"28","毕节":"4","黔西南州":"18","黔东南州":"25","黔南州":"20","保山":"60.0","昭通":"55","丽江":"12","临沧":"36.0","楚雄州":"19","红河州":"43","文山州":"44.0","西双版纳州":"48","大理州":"40.0","德宏州":"48","怒江州":"23","迪庆州":"21","昌都地区":"51","山南地区":"29","日喀则地区":"135.0","那曲地区":"26.0","阿里地区":"4","林芝地区":"18.0","汉中":"54","榆林":"93","安康":"35","商洛":"64","白银":"63","天水":"90","武威":"40","张掖":"64","平凉":"62","酒泉":"42","庆阳":"24","定西":"32","陇南":"45","临夏州":"26","甘南州":"62","海东地区":"42","海北州":"32","黄南州":"79","海南州":"39","果洛州":"46","玉树州":"8.0","海西州":"47","吴忠":"55","中卫":"51","固原":"37","吐鲁番地区":"52","哈密地区":"21.0","昌吉州":"18","博州":"53","阿克苏地区":"66.0","喀什地区":"126","和田地区":"71","伊犁哈萨克州":"48","塔城地区":"22.0","阿勒泰地区":"40.0","石河子":"135.0","五家渠":"7","克州":"67","普洱":"39","襄阳":"147","葫芦岛":"62","河源":"18","揭阳":"25","辽阳":"31","朝阳":"","丹东":"65"},"PM10":{"北京":"277","天津":"223","石家庄":"372","唐山":"341","秦皇岛":"228","邯郸":"174","保定":"458","张家口":"27","承德":"234","廊坊":"276","沧州":"353","衡水":"459","邢台":"518","太原":"99","呼和浩特":"47","沈阳":"127","大连":"114","长春":"103","哈尔滨":"110","上海":"110","南京":"54","苏州":"91","南通":"136","连云港":"166","徐州":"91","扬州":"86","无锡":"103","常州":"91","镇江":"67","泰州":"124","淮安":"119","盐城":"133","宿迁":"123","杭州":"91","宁波":"70","温州":"51","绍兴":"65","湖州":"97","嘉兴":"104","台州":"100","舟山":"46","金华":"44","衢州":"81","丽水":"37","合肥":"48","福州":"17","厦门":"27","南昌":"44","济南":"159","青岛":"149","郑州":"224","武汉":"73","长沙":"","广州":"31","深圳":"41","珠海":"54.0","佛山":"27","中山":"25","江门":"","东莞":"27","惠州":"34","肇庆":"25","南宁":"31","海口":"26","重庆":"62","成都":"48","贵阳":"88","昆明":"34","拉萨":"74","西安":"173","兰州":"43","西宁":"29","银川":"156","乌鲁木齐":"138","湘潭":"82","株洲":"55","包头":"75","鄂尔多斯":"178","营口":"36","盘锦":"106","泉州":"27.0","莱芜":"156","临沂":"143","德州":"406","聊城":"137","滨州":"232","淄博":"172","枣庄":"108","烟台":"127","潍坊":"189","济宁":"128","泰安":"129","日照":"152","威海":"150","东营":"242","韶关":"30","汕头":"27","湛江":"19","茂名":"26","梅州":"24.0","汕尾":"26","阳江":"21","清远":"35","潮州":"61.0","云浮":"15","玉溪":"34","菏泽":"114","大同":"74","长治":"56","临汾":"150","阳泉":"137","赤峰":"74","鞍山":"92","抚顺":"105","本溪":"69","锦州":"107","吉林":"117","齐齐哈尔":"101","牡丹江":"79","大庆":"42","芜湖":"44","马鞍山":"49","九江":"73","洛阳":"244","安阳":"241","开封":"96","焦作":"284","平顶山":"203","三门峡":"209","宜昌":"144","荆州":"178","岳阳":"109","常德":"122","张家界":"117","桂林":"51","北海":"49","柳州":"99","三亚":"26","绵阳":"38","宜宾":"70","攀枝花":"63","泸州":"59","自贡":"74","德阳":"31","南充":"59","遵义":"63","曲靖":"51","咸阳":"148","铜川":"203","延安":"237","宝鸡":"159","渭南":"119","金昌":"76","嘉峪关":"62","石嘴山":"238","克拉玛依":"80","库尔勒":"753.0","寿光":"180","章丘":"150","即墨":"132","胶南":"133","胶州":"113","莱西":"160","平度":"156","蓬莱":"138","招远":"136","莱州":"212","荣成":"91","文登":"110","乳山":"110","吴江":"101","昆山":"110","常熟":"120","张家港":"155","太仓":"117","句容":"55.0","江阴":"136","宜兴":"66","金坛":"71","溧阳":"91","海门":"142","临安":"89","富阳":"79","义乌":"49","诸暨":"","瓦房店":"74","信阳":"92","周口":"119","漳州":"34.0","晋城":"84","朔州":"110","晋中":"244","运城":"136","忻州":"32","吕梁":"105","乌海":"126","通辽":"45","呼伦贝尔":"65","巴彦淖尔":"62","乌兰察布":"47","兴安盟":"67","锡林郭勒盟":"49","阿拉善盟":"208","阜新":"221","铁岭":"138","四平":"148","辽源":"69","通化":"67","白山":"88","松原":"63","白城":"118.0","延边州":"40.0","鸡西":"80","鹤岗":"136","双鸭山":"136","伊春":"44","佳木斯":"90","七台河":"67.0","黑河":"102","绥化":"51","大兴安岭地区":"49.0","蚌埠":"57","淮南":"85","淮北":"71","铜陵":"51","安庆":"57","黄山":"","滁州":"35","阜阳":"44","宿州":"66","六安":"65","亳州":"","池州":"33","宣城":"52","莆田":"39","三明":"31","南平":"46","龙岩":"26","宁德":"19.0","景德镇":"62","萍乡":"115","新余":"65","鹰潭":"36","赣州":"47","吉安":"52","宜春":"57","抚州":"69","上饶":"36","鹤壁":"207","新乡":"286","濮阳":"184","许昌":"203.0","漯河":"156","南阳":"103","商丘":"104","驻马店":"139","黄石":"87","十堰":"86","鄂州":"110","荆门":"187","孝感":"224","黄冈":"92","咸宁":"119","随州":"152","恩施州":"55","衡阳":"81","邵阳":"69","益阳":"77","郴州":"102","永州":"57","怀化":"57","娄底":"95","湘西州":"78","梧州":"37","防城港":"37","钦州":"29","贵港":"46","玉林":"37.0","百色":"72","贺州":"79","河池":"69","来宾":"97","崇左":"43.0","广元":"14","遂宁":"45","内江":"64","乐山":"46","眉山":"55","广安":"60","达州":"92","雅安":"55","巴中":"47","资阳":"55","阿坝州":"48","甘孜州":"32.0","凉山州":"66","六盘水":"151","安顺":"40","铜仁地区":"61","毕节":"8","黔西南州":"72","黔东南州":"43","黔南州":"32","保山":"","昭通":"105","丽江":"47","临沧":"46.0","楚雄州":"32","红河州":"57","文山州":"61.0","西双版纳州":"101","大理州":"29.0","德宏州":"75","怒江州":"29","迪庆州":"32","昌都地区":"120","山南地区":"32","日喀则地区":"123.0","那曲地区":"35.0","阿里地区":"15","林芝地区":"31.0","汉中":"63","榆林":"563","安康":"48","商洛":"106","白银":"164","天水":"120","武威":"137","张掖":"168","平凉":"116","酒泉":"78","庆阳":"130","定西":"47","陇南":"64","临夏州":"51","甘南州":"157","海东地区":"50","海北州":"158","黄南州":"117","海南州":"87","果洛州":"175","玉树州":"42.0","海西州":"255","吴忠":"270","中卫":"211","固原":"134","吐鲁番地区":"183","哈密地区":"110.0","昌吉州":"45","博州":"96","阿克苏地区":"211.0","喀什地区":"341","和田地区":"339","伊犁哈萨克州":"91","塔城地区":"46.0","阿勒泰地区":"48.0","石河子":"","五家渠":"17","克州":"293","普洱":"53","襄阳":"197","葫芦岛":"166","河源":"24","揭阳":"33","辽阳":"72","朝阳":"","丹东":"218"},"SO2":{"北京":"18","天津":"68","石家庄":"85","唐山":"97","秦皇岛":"55","邯郸":"22","保定":"87","张家口":"32","承德":"47","廊坊":"35","沧州":"34","衡水":"28","邢台":"108","太原":"130","呼和浩特":"20","沈阳":"84","大连":"19","长春":"64","哈尔滨":"34","上海":"11","南京":"5","苏州":"9","南通":"11","连云港":"15","徐州":"26","扬州":"13","无锡":"10","常州":"10","镇江":"11","泰州":"26","淮安":"11","盐城":"9","宿迁":"9","杭州":"4","宁波":"10","温州":"1","绍兴":"5","湖州":"1","嘉兴":"9","台州":"3","舟山":"2","金华":"6","衢州":"1","丽水":"3","合肥":"20","福州":"2","厦门":"3","南昌":"6","济南":"39","青岛":"16","郑州":"25","武汉":"13","长沙":"12.0","广州":"2","深圳":"5","珠海":"6.0","佛山":"7","中山":"6","江门":"8.0","东莞":"4","惠州":"7","肇庆":"7","南宁":"9","海口":"3","重庆":"12","成都":"7","贵阳":"39","昆明":"9","拉萨":"11","西安":"30","兰州":"7","西宁":"9","银川":"10","乌鲁木齐":"14","湘潭":"7","株洲":"15","包头":"14","鄂尔多斯":"6","营口":"26","盘锦":"23","泉州":"3.0","莱芜":"55","临沂":"39","德州":"37","聊城":"23","滨州":"69","淄博":"55","枣庄":"41","烟台":"8","潍坊":"42","济宁":"28","泰安":"30","日照":"17","威海":"17","东营":"71","韶关":"10","汕头":"4","湛江":"5","茂名":"4","梅州":"6.0","汕尾":"7","阳江":"2","清远":"12","潮州":"4.0","云浮":"6","玉溪":"10","菏泽":"23","大同":"22","长治":"42","临汾":"105","阳泉":"102","赤峰":"68","鞍山":"31","抚顺":"39","本溪":"49","锦州":"60","吉林":"134","齐齐哈尔":"28","牡丹江":"23","大庆":"14","芜湖":"6","马鞍山":"6","九江":"10","洛阳":"46","安阳":"37","开封":"14","焦作":"96","平顶山":"29","三门峡":"59","宜昌":"23","荆州":"23","岳阳":"28","常德":"8","张家界":"4","桂林":"5","北海":"3","柳州":"14","三亚":"2","绵阳":"8","宜宾":"11","攀枝花":"44","泸州":"9","自贡":"13","德阳":"3","南充":"5","遵义":"15","曲靖":"16","咸阳":"32","铜川":"49","延安":"26","宝鸡":"27","渭南":"34","金昌":"10","嘉峪关":"72","石嘴山":"36","克拉玛依":"3","库尔勒":"9.0","寿光":"50","章丘":"34","即墨":"24","胶南":"6","胶州":"26","莱西":"12","平度":"14","蓬莱":"10","招远":"8","莱州":"9","荣成":"19","文登":"16","乳山":"12","吴江":"5","昆山":"21","常熟":"10","张家港":"11","太仓":"19","句容":"16.0","江阴":"23","宜兴":"7","金坛":"10","溧阳":"5","海门":"15","临安":"3","富阳":"6","义乌":"1","诸暨":"","瓦房店":"23","信阳":"12","周口":"13","漳州":"9.0","晋城":"82","朔州":"84","晋中":"240","运城":"100","忻州":"44","吕梁":"124","乌海":"7","通辽":"13","呼伦贝尔":"5","巴彦淖尔":"33","乌兰察布":"19","兴安盟":"7","锡林郭勒盟":"64","阿拉善盟":"5","阜新":"71","铁岭":"80","四平":"92","辽源":"57","通化":"42","白山":"5","松原":"13","白城":"22.0","延边州":"20.0","鸡西":"81","鹤岗":"6","双鸭山":"20","伊春":"3","佳木斯":"13","七台河":"12.0","黑河":"52","绥化":"81","大兴安岭地区":"53.0","蚌埠":"18","淮南":"22","淮北":"22","铜陵":"53","安庆":"11","黄山":"","滁州":"10","阜阳":"15","宿州":"45","六安":"8","亳州":"18.0","池州":"87","宣城":"25","莆田":"2","三明":"12","南平":"15","龙岩":"4","宁德":"4.0","景德镇":"3","萍乡":"10","新余":"32","鹰潭":"18","赣州":"20","吉安":"2","宜春":"14","抚州":"4","上饶":"8","鹤壁":"48","新乡":"27","濮阳":"6","许昌":"14.0","漯河":"20","南阳":"15","商丘":"21","驻马店":"38","黄石":"4","十堰":"10","鄂州":"3","荆门":"33","孝感":"9","黄冈":"1","咸宁":"10","随州":"11","恩施州":"3","衡阳":"9","邵阳":"13","益阳":"17","郴州":"26","永州":"6","怀化":"10","娄底":"8","湘西州":"1","梧州":"14","防城港":"12","钦州":"6","贵港":"13","玉林":"21.0","百色":"20","贺州":"3","河池":"6","来宾":"10","崇左":"3.0","广元":"10","遂宁":"5","内江":"17","乐山":"4","眉山":"7","广安":"14","达州":"7","雅安":"20","巴中":"5","资阳":"44","阿坝州":"13","甘孜州":"18.0","凉山州":"25","六盘水":"21","安顺":"70","铜仁地区":"4","毕节":"8","黔西南州":"28","黔东南州":"19","黔南州":"39","保山":"4.0","昭通":"10","丽江":"4","临沧":"73.0","楚雄州":"13","红河州":"17","文山州":"7.0","西双版纳州":"12","大理州":"3.0","德宏州":"22","怒江州":"5","迪庆州":"14","昌都地区":"10","山南地区":"6","日喀则地区":"29.0","那曲地区":"30.0","阿里地区":"23","林芝地区":"4.0","汉中":"11","榆林":"6","安康":"16","商洛":"31","白银":"58","天水":"53","武威":"39","张掖":"70","平凉":"36","酒泉":"9","庆阳":"16","定西":"11","陇南":"10","临夏州":"154","甘南州":"11","海东地区":"8","海北州":"18","黄南州":"13","海南州":"14","果洛州":"17","玉树州":"41.0","海西州":"11","吴忠":"7","中卫":"10","固原":"8","吐鲁番地区":"25","哈密地区":"1.0","昌吉州":"10","博州":"19","阿克苏地区":"66.0","喀什地区":"67","和田地区":"701","伊犁哈萨克州":"37","塔城地区":"11.0","阿勒泰地区":"77.0","石河子":"18.0","五家渠":"13","克州":"23","普洱":"14","襄阳":"20","葫芦岛":"43","河源":"3","揭阳":"4","辽阳":"22","朝阳":"","丹东":"43"},"NO2":{"北京":"66","天津":"74","石家庄":"69","唐山":"80","秦皇岛":"54","邯郸":"27","保定":"56","张家口":"9","承德":"63","廊坊":"50","沧州":"59","衡水":"47","邢台":"99","太原":"33","呼和浩特":"11","沈阳":"56","大连":"21","长春":"41","哈尔滨":"97","上海":"25","南京":"24","苏州":"23","南通":"13","连云港":"27","徐州":"20","扬州":"26","无锡":"20","常州":"26","镇江":"24","泰州":"37","淮安":"16","盐城":"9","宿迁":"30","杭州":"25","宁波":"18","温州":"16","绍兴":"29","湖州":"16","嘉兴":"24","台州":"10","舟山":"9","金华":"27","衢州":"13","丽水":"23","合肥":"22","福州":"14","厦门":"11","南昌":"18","济南":"21","青岛":"13","郑州":"60","武汉":"49","长沙":"26.0","广州":"36","深圳":"21","珠海":"25.0","佛山":"17","中山":"17","江门":"17.0","东莞":"20","惠州":"10","肇庆":"8","南宁":"17","海口":"3","重庆":"29","成都":"28","贵阳":"35","昆明":"17","拉萨":"35","西安":"45","兰州":"20","西宁":"17","银川":"6","乌鲁木齐":"80","湘潭":"39","株洲":"16","包头":"9","鄂尔多斯":"6","营口":"15","盘锦":"34","泉州":"12.0","莱芜":"32","临沂":"32","德州":"56","聊城":"25","滨州":"88","淄博":"42","枣庄":"16","烟台":"25","潍坊":"27","济宁":"23","泰安":"32","日照":"30","威海":"26","东营":"67","韶关":"20","汕头":"18","湛江":"8","茂名":"4","梅州":"7.0","汕尾":"12","阳江":"2","清远":"32","潮州":"20.0","云浮":"10","玉溪":"17","菏泽":"18","大同":"15","长治":"34","临汾":"52","阳泉":"59","赤峰":"42","鞍山":"26","抚顺":"40","本溪":"41","锦州":"36","吉林":"36","齐齐哈尔":"43","牡丹江":"25","大庆":"35","芜湖":"13","马鞍山":"20","九江":"18","洛阳":"70","安阳":"52","开封":"28","焦作":"73","平顶山":"57","三门峡":"53","宜昌":"27","荆州":"36","岳阳":"12","常德":"10","张家界":"12","桂林":"28","北海":"12","柳州":"32","三亚":"8","绵阳":"33","宜宾":"24","攀枝花":"49","泸州":"15","自贡":"28","德阳":"29","南充":"17","遵义":"23","曲靖":"11","咸阳":"34","铜川":"47","延安":"39","宝鸡":"49","渭南":"57","金昌":"6","嘉峪关":"49","石嘴山":"10","克拉玛依":"16","库尔勒":"20.0","寿光":"22","章丘":"25","即墨":"9","胶南":"9","胶州":"23","莱西":"16","平度":"24","蓬莱":"20","招远":"12","莱州":"17","荣成":"19","文登":"6","乳山":"4","吴江":"26","昆山":"25","常熟":"31","张家港":"26","太仓":"36","句容":"17.0","江阴":"25","宜兴":"8","金坛":"30","溧阳":"16","海门":"8","临安":"19","富阳":"11","义乌":"14","诸暨":"","瓦房店":"13","信阳":"17","周口":"29","漳州":"23.0","晋城":"30","朔州":"30","晋中":"51","运城":"36","忻州":"18","吕梁":"34","乌海":"9","通辽":"11","呼伦贝尔":"14","巴彦淖尔":"18","乌兰察布":"7","兴安盟":"29","锡林郭勒盟":"9","阿拉善盟":"4","阜新":"43","铁岭":"55","四平":"55","辽源":"37","通化":"55","白山":"32","松原":"20","白城":"24.0","延边州":"23.0","鸡西":"26","鹤岗":"42","双鸭山":"33","伊春":"18","佳木斯":"47","七台河":"28.0","黑河":"35","绥化":"35","大兴安岭地区":"24.0","蚌埠":"28","淮南":"15","淮北":"27","铜陵":"16","安庆":"24","黄山":"","滁州":"17","阜阳":"17","宿州":"16","六安":"10","亳州":"23.0","池州":"24","宣城":"18","莆田":"15","三明":"17","南平":"16","龙岩":"20","宁德":"8.0","景德镇":"9","萍乡":"14","新余":"31","鹰潭":"14","赣州":"33","吉安":"9","宜春":"12","抚州":"15","上饶":"22","鹤壁":"56","新乡":"66","濮阳":"21","许昌":"63.0","漯河":"40","南阳":"16","商丘":"14","驻马店":"40","黄石":"37","十堰":"36","鄂州":"15","荆门":"44","孝感":"30","黄冈":"13","咸宁":"18","随州":"23","恩施州":"19","衡阳":"17","邵阳":"14","益阳":"12","郴州":"30","永州":"26","怀化":"7","娄底":"17","湘西州":"10","梧州":"8","防城港":"10","钦州":"11","贵港":"16","玉林":"17.0","百色":"23","贺州":"20","河池":"16","来宾":"67","崇左":"12.0","广元":"11","遂宁":"19","内江":"29","乐山":"17","眉山":"13","广安":"14","达州":"26","雅安":"18","巴中":"19","资阳":"11","阿坝州":"7","甘孜州":"23.0","凉山州":"26","六盘水":"40","安顺":"9","铜仁地区":"4","毕节":"17","黔西南州":"43","黔东南州":"15","黔南州":"40","保山":"6.0","昭通":"37","丽江":"4","临沧":"25.0","楚雄州":"7","红河州":"8","文山州":"17.0","西双版纳州":"36","大理州":"12.0","德宏州":"23","怒江州":"5","迪庆州":"9","昌都地区":"43","山南地区":"13","日喀则地区":"53.0","那曲地区":"2.0","阿里地区":"6","林芝地区":"6.0","汉中":"30","榆林":"10","安康":"24","商洛":"36","白银":"11","天水":"39","武威":"17","张掖":"26","平凉":"21","酒泉":"17","庆阳":"7","定西":"9","陇南":"9","临夏州":"45","甘南州":"11","海东地区":"10","海北州":"4","黄南州":"8","海南州":"5","果洛州":"6","玉树州":"32.0","海西州":"15","吴忠":"8","中卫":"3","固原":"5","吐鲁番地区":"48","哈密地区":"5.0","昌吉州":"34","博州":"13","阿克苏地区":"54.0","喀什地区":"67","和田地区":"56","伊犁哈萨克州":"62","塔城地区":"37.0","阿勒泰地区":"43.0","石河子":"42.0","五家渠":"24","克州":"32","普洱":"20","襄阳":"36","葫芦岛":"35","河源":"19","揭阳":"9","辽阳":"10","朝阳":"","丹东":"28"}}
